CHANGES
INSTALL
LICENSE
README
setup.py
cisco_decrypt/__init__.py
cisco_decrypt/cisco_decrypt.py
cisco_decrypt.egg-info/PKG-INFO
cisco_decrypt.egg-info/SOURCES.txt
cisco_decrypt.egg-info/dependency_links.txt
cisco_decrypt.egg-info/top_level.txt
