Metadata-Version: 1.0
Name: cisco-decrypt
Version: 0.8.3
Summary: decrypt Cisco Type 7 passwords
Home-page: http://www.pennington.net/py/cisco_decrypt/
Author: David Michael Pennington
Author-email: mike /|at|\ pennington.net
License: GPL
Keywords: Decrypt IOS Type 7 password
Platform: UNKNOWN
Classifier: Development Status :: 4 - Beta
Classifier: Environment :: Plugins
Classifier: Intended Audience :: Developers
Classifier: Intended Audience :: System Administrators
Classifier: Intended Audience :: Information Technology
Classifier: Intended Audience :: Telecommunications Industry
Classifier: License :: OSI Approved :: GNU General Public License (GPL)
Classifier: Natural Language :: English
Classifier: Operating System :: OS Independent
Classifier: Programming Language :: Python
Classifier: Topic :: Communications
Classifier: Topic :: Internet
Classifier: Topic :: System :: Networking
Classifier: Topic :: System :: Networking :: Monitoring
Classifier: Topic :: Software Development :: Libraries :: Python Modules
